capitalcom/__init__.py
capitalcom/client.py
capitalcom-1.0.3.dist-info/METADATA
capitalcom-1.0.3.dist-info/WHEEL
capitalcom-1.0.3.dist-info/top_level.txt
capitalcom-1.0.3.dist-info/RECORD
