Metadata-Version: 2.4
Name: capitalcom
Version: 1.0.3
Summary: Client for Capital.com REST API (demo and real)
Author-email: Wikto Jelen <wiktor.dev@yelon.ovh>
License: CC BY-NC 4.0
Project-URL: homepage, https://github.com/Akinzou/CapitalCom
Project-URL: discord, https://discord.gg/BARYa55KS8
Classifier: Programming Language :: Python :: 3
Classifier: License :: OSI Approved :: MIT License
Classifier: Operating System :: OS Independent
Requires-Python: >=3.8
Requires-Dist: requests>=2.25
